cerebellar_models/__init__.py
cerebellar_models/cli.py
cerebellar_models/utils.py
cerebellar_models/analysis/__init__.py
cerebellar_models/analysis/plots.py
cerebellar_models/analysis/report.py
cerebellar_models/analysis/spiking_results.py
cerebellar_models/analysis/structure_analysis.py
cerebellar_models/connectome/__init__.py
cerebellar_models/connectome/glomerulus_golgi.py
cerebellar_models/connectome/glomerulus_granule.py
cerebellar_models/connectome/glomerulus_ubc.py
cerebellar_models/connectome/golgi_glomerulus.py
cerebellar_models/connectome/io_molecular.py
cerebellar_models/connectome/io_purkinje.py
cerebellar_models/connectome/presyn_dist_strat.py
cerebellar_models/connectome/to_glomerulus.py
cerebellar_models/nest_models/__init__.py
cerebellar_models/nest_models/build_models.py
cerebellar_models/nest_models/eglif_cond_alpha_multisyn.nestml
cerebellar_models/placement/__init__.py
cerebellar_models/placement/microzones.py
cerebellar_models-0.9.0.dist-info/entry_points.txt
cerebellar_models-0.9.0.dist-info/licenses/LICENSE
cerebellar_models-0.9.0.dist-info/WHEEL
cerebellar_models-0.9.0.dist-info/METADATA
cerebellar_models-0.9.0.dist-info/RECORD
