Metadata-Version: 2.4
Name: cerebellar-models
Version: 0.9.0
Summary: Implementation of the BSB framework for cerebellar cortex reconstructions and simulations.
Author-email: Dimitri RODARIE <dimitri.rodarie@unipv.it>
Requires-Python: >=3.10
Classifier: License :: OSI Approved :: GNU General Public License v3 or later (GPLv3+)
License-File: LICENSE
Requires-Dist: bsb[parallel, nest, neuron]~=7.0
Requires-Dist: nestml~=8.2
Requires-Dist: click~=8.1
Requires-Dist: survey~=5.4.2
Requires-Dist: matplotlib~=3.9
Requires-Dist: elephant~=1.1
Requires-Dist: cerebellar-models[test, docs] ; extra == "dev"
Requires-Dist: pre-commit~=3.5 ; extra == "dev"
Requires-Dist: black~=25.1.0 ; extra == "dev"
Requires-Dist: isort~=6.0.0 ; extra == "dev"
Requires-Dist: bump-my-version~=0.21 ; extra == "dev"
Requires-Dist: sphinx~=8.1 ; extra == "docs"
Requires-Dist: furo~=2024.0 ; extra == "docs"
Requires-Dist: bsb-test~=7.0 ; extra == "test"
Requires-Dist: coverage~=7.3 ; extra == "test"
Project-URL: Bug Tracker, https://github.com/dbbs-lab/cerebellar-models/issues/
Project-URL: Home, https://github.com/dbbs-lab/cerebellar-models
Project-URL: Source Code, https://github.com/dbbs-lab/cerebellar-models/
Provides-Extra: dev
Provides-Extra: docs
Provides-Extra: test
